delfino/__init__.py
delfino/click_utils/__init__.py
delfino/click_utils/command.py
delfino/click_utils/command_groups.py
delfino/click_utils/set_from_config.py
delfino/config.py
delfino/constants.py
delfino/decorators/__init__.py
delfino/decorators/files_folders.py
delfino/decorators/pass_app_context.py
delfino/decorators/pass_args.py
delfino/execution.py
delfino/internal_parameters/__init__.py
delfino/internal_parameters/completion.py
delfino/internal_parameters/help.py
delfino/internal_parameters/verbosity.py
delfino/main.py
delfino/models/__init__.py
delfino/models/app_context.py
delfino/models/pyproject_toml.py
delfino/terminal_output.py
delfino/utils.py
delfino/validation.py
delfino-5.1.0.dist-info/WHEEL
delfino-5.1.0.dist-info/entry_points.txt
delfino-5.1.0.dist-info/METADATA
delfino-5.1.0.dist-info/RECORD
