Metadata-Version: 2.3
Name: delfino
Version: 5.1.0
Summary: A collection of command line helper scripts wrapping tools used during Python development.
Author: Radek Lát
Author-email: Radek Lát <radek.lat@gmail.com>
License: MIT License
Classifier: Development Status :: 4 - Beta
Classifier: Environment :: Console
Classifier: Intended Audience :: Developers
Classifier: License :: OSI Approved :: MIT License
Classifier: Operating System :: OS Independent
Classifier: Programming Language :: Python :: 3
Classifier: Programming Language :: Python :: 3 :: Only
Classifier: Programming Language :: Python :: 3.10
Classifier: Programming Language :: Python :: 3.11
Classifier: Programming Language :: Python :: 3.12
Classifier: Programming Language :: Python :: 3.13
Classifier: Topic :: Software Development
Classifier: Topic :: Utilities
Requires-Dist: toml>=0.10
Requires-Dist: click>=8.2.0
Requires-Dist: pydantic>=2.0
Requires-Dist: deprecation>=2.1
Requires-Dist: shellingham>=1.4 ; extra == 'completion'
Requires-Python: >=3.10.0
Provides-Extra: completion
